static_bundler/__init__.py
static_bundler/bundle.py
static_bundler-0.0.2.dist-info/LICENSE.rst
static_bundler-0.0.2.dist-info/METADATA
static_bundler-0.0.2.dist-info/WHEEL
static_bundler-0.0.2.dist-info/top_level.txt
static_bundler-0.0.2.dist-info/RECORD
