Metadata-Version: 2.1
Name: static-bundler
Version: 0.0.2
Summary: Bundles multiple css/js files into one and reduce request time
Home-page: 
Author: Saad Abdullah
Author-email: Saad Abdullah <saadfast.qc@gmail.com>
License: MIT License        
Project-URL: Homepage, https://github.com/saadqc/bundler.git
Project-URL: Bug Tracker, https://github.com/saadqc/bundler/issues
Keywords: bundler,bundles,minify,static
Classifier: Programming Language :: Python :: 3
Classifier: License :: OSI Approved :: MIT License
Classifier: Operating System :: OS Independent
Requires-Python: >=3.5
License-File: LICENSE.rst
Requires-Dist: Jinja2 (>=2.9.3)
Requires-Dist: lxml (>=3.8.0)
Requires-Dist: setuptools (>=31.0.0)
Requires-Dist: Flask (>=1.0.1)
